Scanner/Scanner.py
Scanner/__init__.py
FileScaner-1.1.dist-info/METADATA
FileScaner-1.1.dist-info/WHEEL
FileScaner-1.1.dist-info/top_level.txt
FileScaner-1.1.dist-info/RECORD
