Metadata-Version: 2.1
Name: FileScaner
Version: 1.1
Summary: Scan files based on file type
Author: Ryan Sanders
Author-email: rasanders22@gmail.com
Keywords: python,scans files
Classifier: Development Status :: 3 - Alpha
Classifier: Intended Audience :: Education
Classifier: Programming Language :: Python :: 2
Classifier: Programming Language :: Python :: 3
Classifier: Operating System :: MacOS :: MacOS X
Classifier: Operating System :: Microsoft :: Windows
Requires-Dist: pandas
Requires-Dist: pathlib
